mysbox-0.1.dist-info/WHEEL
mysbox-0.1.dist-info/metadata.json
mysbox-0.1.dist-info/top_level.txt
mysbox-0.1.dist-info/RECORD
mysbox-0.1.dist-info/DESCRIPTION.rst
mysbox-0.1.dist-info/entry_points.txt
mysbox-0.1.dist-info/METADATA
mysbox/compile.py
mysbox/__init__.py
mysbox/create.py
mysbox/config.py
mysbox/upload.py
mysbox/skeletons/.mysboxrc.skeleton
mysbox/skeletons/node_16.ino
mysbox/skeletons/gw_serial_16.ino
