Metadata-Version: 2.0
Name: mysbox
Version: 0.1
Summary: It is a module to make easier communication with MySensor's network.
Home-page: https://github.com/alfredocdmiranda/mysbox
Author: Alfredo Miranda
Author-email: alfredocdmiranda@gmail.com
License: LGPLv3
Keywords: MYS MySensors
Platform: UNKNOWN
Classifier: Development Status :: 3 - Alpha
Classifier: Intended Audience :: Developers
Classifier: Intended Audience :: End Users/Desktop
Classifier: License :: OSI Approved :: GNU Lesser General Public License v3 (LGPLv3)
Classifier: Operating System :: POSIX :: Linux
Classifier: Programming Language :: Python
Classifier: Programming Language :: Python :: 3
Classifier: Programming Language :: Python :: 3.4
Classifier: Topic :: Home Automation
Classifier: Topic :: Software Development :: Build Tools
Classifier: Topic :: Utilities
Requires-Dist: pyserial (>=2.7)
Requires-Dist: jinja2 (>=2.8)
